databand/__init__.py
databand/__main__.py
databand/commands.py
databand/errors.py
databand/parameters.py
databand/tasks/__init__.py
databand/tasks/basics/__init__.py
dbnd_run/__init__.py
dbnd_run/current.py
dbnd_run/orchestration_bootstrap.py
dbnd_run/_vendor/__init__.py
dbnd_run/_vendor/database.py
dbnd_run/_vendor/kubernetes_utils.py
dbnd_run/airflow/__init__.py
dbnd_run/airflow/airflow_env.py
dbnd_run/airflow/airflow_utils.py
dbnd_run/airflow/config.py
dbnd_run/airflow/constants.py
dbnd_run/airflow/db_utils.py
dbnd_run/airflow/utils.py
dbnd_run/airflow/airflow_extensions/__init__.py
dbnd_run/airflow/airflow_extensions/dal.py
dbnd_run/airflow/airflow_override/__init__.py
dbnd_run/airflow/airflow_override/dbnd_airflow_windows/__init__.py
dbnd_run/airflow/airflow_override/dbnd_airflow_windows/airflow_windows_support.py
dbnd_run/airflow/airflow_override/dbnd_airflow_windows/configuration.py
dbnd_run/airflow/airflow_override/dbnd_airflow_windows/getuser.py
dbnd_run/airflow/airflow_override/dbnd_airflow_windows/timeout.py
dbnd_run/airflow/compat/__init__.py
dbnd_run/airflow/compat/airflow_multi_version_shim.py
dbnd_run/airflow/compat/cli_factory.py
dbnd_run/airflow/compat/dbnd_task_runner.py
dbnd_run/airflow/compat/kubernetes_executor.py
dbnd_run/airflow/dbnd_airflow_contrib/README.md
dbnd_run/airflow/dbnd_airflow_contrib/__init__.py
dbnd_run/airflow/dbnd_airflow_contrib/credentials_helper_aws.py
dbnd_run/airflow/dbnd_airflow_contrib/credentials_helper_azure.py
dbnd_run/airflow/dbnd_airflow_contrib/credentials_helper_gcp.py
dbnd_run/airflow/dbnd_airflow_contrib/dbnd_airflow_default_logger.py
dbnd_run/airflow/dbnd_airflow_contrib/dbnd_operator.py
dbnd_run/airflow/dbnd_airflow_contrib/docker_operator.py
dbnd_run/airflow/dbnd_airflow_contrib/kubernetes_metrics_logger.py
dbnd_run/airflow/dbnd_airflow_contrib/mng_connections.py
dbnd_run/airflow/dbnd_airflow_contrib/safe_hostname_name.py
dbnd_run/airflow/dbnd_airflow_contrib/utils/__init__.py
dbnd_run-1.0.30.1.dist-info/LICENSE
dbnd_run-1.0.30.1.dist-info/METADATA
dbnd_run-1.0.30.1.dist-info/WHEEL
dbnd_run-1.0.30.1.dist-info/entry_points.txt
dbnd_run-1.0.30.1.dist-info/top_level.txt
dbnd_run-1.0.30.1.dist-info/RECORD
