Metadata-Version: 2.1
Name: dbnd-run
Version: 1.0.30.1
Summary: Machine Learning Orchestration
Home-page: https://github.com/databand-ai/dbnd
Author: Evgeny Shulman
Author-email: evgeny.shulman@databand.ai
Maintainer: Evgeny Shulman
Maintainer-email: evgeny.shulman@databand.ai
Project-URL: Documentation, https://dbnd.readme.io/
Project-URL: Bug-Tracker, https://github.com/databand-ai/dbnd/issues
Project-URL: Source-Code, https://github.com/databand-ai/dbnd
Keywords: orchestration,data,machinelearning
Platform: any
Classifier: Development Status :: 4 - Beta
Classifier: Intended Audience :: Developers
Classifier: Natural Language :: English
Classifier: License :: OSI Approved :: Apache Software License
Classifier: Operating System :: OS Independent
Classifier: Programming Language :: Python
Classifier: Programming Language :: Python :: 3
Classifier: Programming Language :: Python :: 3.7
Classifier: Programming Language :: Python :: 3.8
Classifier: Programming Language :: Python :: 3.9
Classifier: Programming Language :: Python :: 3.10
Classifier: Programming Language :: Python :: 3.11
Classifier: Programming Language :: Python :: Implementation :: CPython
Classifier: Programming Language :: Python :: Implementation :: PyPy
Classifier: Topic :: Software Development :: Libraries :: Python Modules
License-File: LICENSE
Requires-Dist: dbnd (==1.0.30.1)
Requires-Dist: packaging
Provides-Extra: test-pandas
Requires-Dist: numpy (<1.23) ; extra == 'test-pandas'
Requires-Dist: pandas (<2.0.0,>=0.17.1) ; extra == 'test-pandas'
Provides-Extra: test-providers
Requires-Dist: openpyxl (==2.6.4) ; extra == 'test-providers'
Requires-Dist: numpy (<1.23) ; extra == 'test-providers'
Requires-Dist: pandas (<2.0.0,>=0.17.1) ; extra == 'test-providers'
Requires-Dist: tables (==3.7.0) ; extra == 'test-providers'
Requires-Dist: feather-format ; extra == 'test-providers'
Requires-Dist: pyarrow ; extra == 'test-providers'
Requires-Dist: matplotlib (==3.3.0) ; (python_version < "3.8") and extra == 'test-providers'
Requires-Dist: matplotlib (==3.6.2) ; (python_version >= "3.8") and extra == 'test-providers'
Provides-Extra: tests
Requires-Dist: pytest (==6.2.5) ; extra == 'tests'
Requires-Dist: coverage (==7.0.1) ; extra == 'tests'
Requires-Dist: pytest-cov (==3.0.0) ; extra == 'tests'
Requires-Dist: boto3 ; extra == 'tests'
Requires-Dist: mock ; extra == 'tests'
Requires-Dist: sh ; extra == 'tests'
